ipypng/__init__.py
ipypng/ipypng.py
iPyPNG-1.0.1.dist-info/LICENSE
iPyPNG-1.0.1.dist-info/METADATA
iPyPNG-1.0.1.dist-info/WHEEL
iPyPNG-1.0.1.dist-info/top_level.txt
iPyPNG-1.0.1.dist-info/RECORD
