Metadata-Version: 2.1
Name: iPyPNG
Version: 1.0.1
Summary: Convert real PNG to Apple fake PNG (CgBI)
Home-page: https://github.com/HGStyle/iPyPNG
Author: HGStyle
Author-email: hgstyle@outlook.fr
Project-URL: Documentation, https://github.com/HGStyle/iPyPNG
Keywords: CgBI
Classifier: Development Status :: 5 - Production/Stable
Classifier: Programming Language :: Python :: 3.9
Classifier: Programming Language :: Python :: 3.10
Classifier: Programming Language :: Python :: 3.11
Classifier: Programming Language :: Python :: Implementation :: CPython
Classifier: Programming Language :: Python :: Implementation :: PyPy
Classifier: Intended Audience :: Developers
Classifier: License :: OSI Approved :: MIT License
Classifier: Topic :: Scientific/Engineering :: Image Processing
Requires-Python: >=3.9
License-File: LICENSE
